users_and_computers/__init__.py
users_and_computers/filtersets.py
users_and_computers/forms.py
users_and_computers/graphql.py
users_and_computers/models.py
users_and_computers/navigation.py
users_and_computers/tables.py
users_and_computers/template_content.py
users_and_computers/urls.py
users_and_computers/version.py
users_and_computers/views.py
users_and_computers/api/__init__.py
users_and_computers/api/serializers.py
users_and_computers/api/urls.py
users_and_computers/api/views.py
users_and_computers/migrations/0001_initial.py
users_and_computers/migrations/__init__.py
users_and_computers/templates/users_and_computers/aduser.html
users_and_computers/templates/users_and_computers/risk.html
users_and_computers/templates/users_and_computers/risk_panel.html
users_and_computers/templates/users_and_computers/riskassignment_edit.html
users_and_computers/templates/users_and_computers/riskrelation.html
netbox_users_and_computers-0.8.5.dist-info/LICENSE
netbox_users_and_computers-0.8.5.dist-info/METADATA
netbox_users_and_computers-0.8.5.dist-info/WHEEL
netbox_users_and_computers-0.8.5.dist-info/top_level.txt
netbox_users_and_computers-0.8.5.dist-info/RECORD
