Metadata-Version: 2.1
Name: netbox-users-and-computers
Version: 0.8.5
Summary: Netbox plugin. Manage AD Users and Workstations
Download-URL: https://pypi.org/project/netbox-users-and-computers/
Author: Artur Shamsiev
Author-email: me@z-lab.me
Maintainer: Artur Shamsiev
Maintainer-email: me@z-lab.me
License: MIT
Keywords: netbox,netbox-plugin
Classifier: Programming Language :: Python :: 3.10
Classifier: License :: OSI Approved :: MIT License
Classifier: Operating System :: OS Independent
Requires-Python: >=3.8
License-File: LICENSE
